[
  {
    "_id": "665dbc010000000000000001",
    "question": "Chuỗi số sau tuân theo quy luật nào: 3, 6, 12, 24, ?",
    "level": 1,
    "tag_ids": ["665dbc000000000000000001"],
    "type": "multiple_choice",
    "choices": [
      { "text": "36", "is_correct": false },
      { "text": "48", "is_correct": true },
      { "text": "60", "is_correct": false }
    ],
    "answer_explanation": "Chuỗi số 3, 6, 12, 24 có quy luật mỗi số được nhân đôi để ra số tiếp theo.\n3 × 2 = 6.\n6 × 2 = 12.\n12 × 2 = 24.\nDo đó, 24 × 2 = 48 là số tiếp theo.\nCác lựa chọn khác không phù hợp với quy luật này.\nQuy luật nhân đôi là một mẫu đơn giản, thường gặp trong các bài toán nhận diện mẫu.",
    "createdAt": "2025-05-12T10:00:00Z",
    "updatedAt": "2025-05-12T10:00:00Z"
  },
  {
    "_id": "665dbc010000000000000002",
    "question": "Hình tiếp theo trong chuỗi hình vuông, tam giác, hình tròn, hình vuông, ? là gì?",
    "level": 2,
    "tag_ids": ["665dbc000000000000000001"],
    "type": "multiple_choice",
    "choices": [
      { "text": "Tam giác", "is_correct": true },
      { "text": "Hình tròn", "is_correct": false },
      { "text": "Hình vuông", "is_correct": false }
    ],
    "answer_explanation": "Chuỗi hình vuông, tam giác, hình tròn, hình vuông có quy luật lặp lại.\nBa hình đầu (vuông, tam giác, tròn) tạo thành một chu kỳ.\nHình thứ tư (vuông) bắt đầu chu kỳ mới.\nDo đó, hình tiếp theo là tam giác (theo thứ tự chu kỳ).\nCác lựa chọn khác không phù hợp với mẫu lặp lại này.\nNhận diện mẫu dựa trên thứ tự lặp lại là kỹ năng quan trọng trong bài toán này.",
    "createdAt": "2025-05-12T10:00:00Z",
    "updatedAt": "2025-05-12T10:00:00Z"
  },
  {
    "_id": "665dbc010000000000000003",
    "question": "Chuỗi chữ cái A, C, I, I, ? có chữ cái tiếp theo là gì?",
    "level": 3,
    "tag_ids": ["665dbc000000000000000001"],
    "type": "multiple_choice",
    "choices": [
      { "text": "I", "is_correct": false },
      { "text": "A", "is_correct": true },
      { "text": "C", "is_correct": false }
    ],
    "answer_explanation": "Chuỗi A, C, I, I có quy luật lặp lại sau bốn phần tử.\nA là chữ cái thứ 1, C là thứ 3, I là thứ 9 trong bảng chữ cái.\nVị trí thứ tư lặp lại I.\nChu kỳ bốn phần tử là A, C, I, I.\nDo đó, phần tử tiếp theo là A (bắt đầu chu kỳ mới).\nCác lựa chọn khác không phù hợp với mẫu này.\nNhận diện mẫu chữ cái yêu cầu chú ý đến thứ tự và chu kỳ lặp lại.",
    "createdAt": "2025-05-12T10:00:00Z",
    "updatedAt": "2025-05-12T10:00:00Z"
  },
  {
    "_id": "665dbc010000000000000004",
    "question": "Chuỗi 1, 4, 9, 16, ? có số tiếp theo là gì?",
    "level": 2,
    "tag_ids": ["665dbc000000000000000001"],
    "type": "multiple_choice",
    "choices": [
      { "text": "25", "is_correct": true },
      { "text": "20", "is_correct": false },
      { "text": "36", "is_correct": false }
    ],
    "answer_explanation": "Chuỗi 1, 4, 9, 16 là các số bình phương: 1², 2², 3², 4².\nSố tiếp theo là 5² = 25.\nQuy luật là bình phương của các số tự nhiên liên tiếp.\nLựa chọn 20 và 36 không phải là số bình phương của số tự nhiên nào.\nNhận diện mẫu số học yêu cầu hiểu các dạng toán học cơ bản như bình phương.\nViệc kiểm tra các số tiếp theo giúp xác nhận quy luật.",
    "createdAt": "2025-05-12T10:00:00Z",
    "updatedAt": "2025-05-12T10:00:00Z"
  },
  {
    "_id": "665dbc010000000000000005",
    "question": "Chuỗi màu sắc đỏ, xanh, vàng, đỏ, ? có màu tiếp theo là gì?",
    "level": 1,
    "tag_ids": ["665dbc000000000000000001"],
    "type": "multiple_choice",
    "choices": [
      { "text": "Xanh", "is_correct": true },
      { "text": "Vàng", "is_correct": false },
      { "text": "Đỏ", "is_correct": false }
    ],
    "answer_explanation": "Chuỗi đỏ, xanh, vàng, đỏ có quy luật lặp lại sau ba màu.\nBa màu đầu (đỏ, xanh, vàng) tạo thành một chu kỳ.\nMàu thứ tư (đỏ) bắt đầu chu kỳ mới.\nDo đó, màu tiếp theo là xanh (theo thứ tự chu kỳ).\nCác lựa chọn khác không phù hợp với mẫu lặp lại này.\nNhận diện mẫu màu sắc dựa trên chu kỳ lặp là bài toán đơn giản nhưng cần chú ý.",
    "createdAt": "2025-05-12T10:00:00Z",
    "updatedAt": "2025-05-12T10:00:00Z"
  },
  {
    "_id": "665dbc010000000000000006",
    "question": "Số tiếp theo trong dãy 5, 10, 20, 35, ? là gì?",
    "level": 3,
    "tag_ids": ["665dbc000000000000000002"],
    "type": "multiple_choice",
    "choices": [
      { "text": "50", "is_correct": true },
      { "text": "45", "is_correct": false },
      { "text": "60", "is_correct": false }
    ],
    "answer_explanation": "Dãy 5, 10, 20, 35 có quy luật: mỗi số được tính bằng số trước cộng với một số tăng dần.\n5 + 5 = 10.\n10 + 10 = 20.\n20 + 15 = 35.\nSố cộng thêm lần lượt là 5, 10, 15, tăng 5 mỗi lần.\nSố tiếp theo là 35 + 20 = 50.\nCác lựa chọn khác không phù hợp với quy luật này.\nPhân tích dãy số yêu cầu nhận diện mẫu số cộng thêm và dự đoán số tiếp theo.",
    "createdAt": "2025-05-12T10:00:00Z",
    "updatedAt": "2025-05-12T10:00:00Z"
  },
  {
    "_id": "665dbc010000000000000007",
    "question": "Số tiếp theo trong dãy 2, 5, 11, 23, ? là gì?",
    "level": 4,
    "tag_ids": ["665dbc000000000000000002"],
    "type": "multiple_choice",
    "choices": [
      { "text": "44", "is_correct": true },
      { "text": "48", "is_correct": false },
      { "text": "50", "is_correct": false }
    ],
    "answer_explanation": "Dãy 2, 5, 11, 23 có quy luật: mỗi số được nhân đôi rồi cộng thêm 1.\n2 × 2 + 1 = 5.\n5 × 2 + 1 = 11.\n11 × 2 + 1 = 23.\nDo đó, 23 × 2 + 1 = 44 là số tiếp theo.\nCác lựa chọn khác không tuân theo quy luật này.\nPhân tích dãy số phức tạp hơn này yêu cầu nhận diện cả phép nhân và cộng.\nKiểm tra từng bước giúp xác nhận quy luật chính xác.",
    "createdAt": "2025-05-12T10:00:00Z",
    "updatedAt": "2025-05-12T10:00:00Z"
  },
  {
    "_id": "665dbc010000000000000008",
    "question": "Dãy 1, 3, 6, 10, ? có số tiếp theo là gì?",
    "level": 2,
    "tag_ids": ["665dbc000000000000000002"],
    "type": "multiple_choice",
    "choices": [
      { "text": "15", "is_correct": true },
      { "text": "12", "is_correct": false },
      { "text": "18", "is_correct": false }
    ],
    "answer_explanation": "Dãy 1, 3, 6, 10 là dãy số tam giác, tính bằng công thức n(n+1)/2.\nSố thứ nhất: 1(1+1)/2 = 1.\nSố thứ hai: 2(2+1)/2 = 3.\nSố thứ ba: 3(3+1)/2 = 6.\nSố thứ tư: 4(4+1a = 6.\nSố thứ năm: 5(5+1)/2 = 15.\nCác lựa chọn khác không phù hợp.\nDãy số tam giác là một dạng dãy số phổ biến trong bài toán logic.",
    "createdAt": "2025-05-12T10:00:00Z",
    "updatedAt": "2025-05-12T10:00:00Z"
  },
  {
    "_id": "665dbc010000000000000009",
    "question": "Số tiếp theo trong dãy 4, 7, 11, 16, ? là gì?",
    "level": 2,
    "tag_ids": ["665dbc000000000000000002"],
    "type": "multiple_choice",
    "choices": [
      { "text": "22", "is_correct": true },
      { "text": "20", "is_correct": false },
      { "text": "25", "is_correct": false }
    ],
    "answer_explanation": "Dãy 4, 7, 11, 16 có quy luật: mỗi số được cộng thêm một số tăng dần.\n4 + 3 = 7.\n7 + 4 = 11.\n11 + 5 = 16.\nSố cộng thêm tăng 1 mỗi lần (3, 4, 5).\nDo đó, 16 + 6 = 22 là số tiếp theo.\nCác lựa chọn khác không phù hợp với quy luật.\nPhân tích dãy số yêu cầu nhận diện mẫu số cộng thêm và dự đoán số tiếp theo.\nKiểm tra kỹ giúp tránh nhầm lẫn với các mẫu khác.",
    "createdAt": "2025-05-12T10:00:00Z",
    "updatedAt": "2025-05-12T10:00:00Z"
  },
  {
    "_id": "665dbc01000000000000000a",
    "question": "Số tiếp theo trong dãy 1, 2, 4, 7, ? là gì?",
    "level": 3,
    "tag_ids": ["665dbc000000000000000002"],
    "type": "multiple_choice",
    "choices": [
      { "text": "11", "is_correct": true },
      { "text": "10", "is_correct": false },
      { "text": "13", "is_correct": false }
    ],
    "answer_explanation": "Dãy 1, 2, 4, 7 có quy luật: mỗi số được cộng thêm một số tăng dần.\n1 + 1 = 2.\n2 + 2 = 4.\n4 + 3 = 7.\nSố cộng thêm tăng 1 mỗi lần (1, 2, 3).\nDo đó, 7 + 4 = 11 là số tiếp theo.\nCác lựa chọn khác không phù hợp với quy luật.\nPhân tích dãy số yêu cầu nhận diện mẫu số cộng thêm và dự đoán chính xác.\nKiểm tra từng bước đảm bảo độ chính xác của quy luật.",
    "createdAt": "2025-05-12T10:00:00Z",
    "updatedAt": "2025-05-12T10:00:00Z"
  },
  {
    "_id": "665dbc01000000000000000b",
    "question": "Mèo : Mèo con :: Chó : ?",
    "level": 1,
    "tag_ids": ["665dbc000000000000000003"],
    "type": "multiple_choice",
    "choices": [
      { "text": "Chó con", "is_correct": true },
      { "text": "Chó lớn", "is_correct": false },
      { "text": "Mèo con", "is_correct": false }
    ],
    "answer_explanation": "Tương đồng Mèo : Mèo con là mối quan hệ mẹ-con.\nMèo là mẹ, mèo con là con.\nTương tự, Chó là mẹ, chó con là con.\nDo đó, đáp án đúng là Chó con.\nCác lựa chọn khác không thể hiện mối quan hệ mẹ-con.\nTương đồng yêu cầu nhận diện mối quan hệ logic giữa các cặp từ.\nKiểm tra mối quan hệ giúp xác định đáp án chính xác.",
    "createdAt": "2025-05-12T10:00:00Z",
    "updatedAt": "2025-05-12T10:00:00Z"
  },
  {
    "_id": "665dbc01000000000000000c",
    "question": "Bút : Viết :: Dao : ?",
    "level": 3,
    "tag_ids": ["665dbc000000000000000003"],
    "type": "multiple_choice",
    "choices": [
      { "text": "Recall", "is_correct": true },
      { "text": "Focus", "is_correct": false },
      { "text": "Logic", "is_correct": false }
    ],
    "answer_explanation": "Tương đồng Concentration : Attention là mối quan hệ khái niệm-kỹ năng.\nConcentration (tập trung) liên quan đến kỹ năng attention (chú ý).\nTương tự, Memory (trí nhớ) liên quan đến kỹ năng recall (hồi tưởng).\nDo đó, đáp án đúng là Recall.\nCác lựa chọn khác không thể hiện mối quan hệ tương tự.\nTương đồng yêu cầu nhận diện mối quan hệ giữa khái niệm và kỹ năng.\nKiểm tra ý nghĩa của từng từ giúp xác định đáp án chính xác.",
    "createdAt": "2025-05-12T10:00:00Z",
    "updatedAt": "2025-05-12T10:00:00Z"
  },
  {
    "_id": "665dbc01000000000000000e",
    "question": "Cây : Lá :: Nhà : ?",
    "level": 2,
    "tag_ids": ["665dbc000000000000000003"],
    "type": "multiple_choice",
    "choices": [
      { "text": "Mái", "is_correct": true },
      { "text": "Cửa", "is_correct": false },
      { "text": "Tường", "is_correct": false }
    ],
    "answer_explanation": "Tương đồng Cây : Lá là mối quan hệ tổng thể-phần.\nLá là một phần quan trọng của cây.\nTương tự, mái là một phần quan trọng của nhà.\nDo đó, đáp án đúng là Mái.\nCác lựa chọn khác tuy là phần của nhà nhưng không mang tính đại diện như mái.\nTương đồng yêu cầu nhận diện mối quan hệ tổng thể-phần.\nKiểm tra vai trò của từng phần giúp xác định đáp án.",
    "createdAt": "2025-05-12T10:00:00Z",
    "updatedAt": "2025-05-12T10:00:00Z"
  },
  {
    "_id": "665dbc01000000000000000f",
    "question": "Sông : Nước :: Đường : ?",
    "level": 1,
    "tag_ids": ["665dbc000000000000000003"],
    "type": "multiple_choice",
    "choices": [
      { "text": "Xe", "is_correct": true },
      { "text": "Cây", "is_correct": false },
      { "text": "Đá", "is_correct": false }
    ],
    "answer_explanation": "Tương đồng Sông : Nước là mối quan hệ môi trường-yếu tố chính.\nSông chứa nước.\nTương tự, đường là nơi xe di chuyển.\nDo đó, đáp án đúng là Xe.\nCác lựa chọn khác không phải yếu tố chính trên đường.\nTương đồng yêu cầu nhận diện mối quan hệ giữa môi trường và yếu tố chính.\nKiểm tra yếu tố chính của môi trường giúp xác định đáp án.",
    "createdAt": "2025-05-12T10:00:00Z",
    "updatedAt": "2025-05-12T10:00:00Z"
  },
  {
    "_id": "665dbc010000000000000010",
    "question": "Tất cả chim đều có cánh. Tất cả đại bàng là chim. Kết luận là gì?",
    "level": 1,
    "tag_ids": ["665dbc000000000000000004"],
    "type": "multiple_choice",
    "choices": [
      { "text": "Tất cả đại bàng có cánh", "is_correct": true },
      { "text": "Tất cả đại bàng không có cánh", "is_correct": false },
      { "text": "Một số đại bàng có cánh", "is_correct": false }
    ],
    "answer_explanation": "Tiền đề 1 od: Tất cả chim đều có cánh.\nTiền đề 2: Tất cả đại bàng là chim.\nTừ tiền đề 1, ta biết mọi chim đều có cánh.\nTừ tiền đề 2, đại bàng thuộc nhóm chim.\nDo đó, suy luận diễn dịch cho thấy tất cả đại bàng có cánh.\nLựa chọn khác mâu thuẫn với tiền đề.\nSuy luận diễn dịch yêu cầu rút ra kết luận logic từ các tiền đề.\nKiểm tra tính hợp lệ của kết luận đảm bảo đáp án đúng.",
    "createdAt": "2025-05-12T10:00:00Z",
    "updatedAt": "2025-05-12T10:00:00Z"
  },
  {
    "_id": "665dbc010000000000000011",
    "question": "Nếu trời mưa, đường ướt. Trời không mưa. Đường có ướt không?",
    "level": 2,
    "tag_ids": ["665dbc000000000000000004"],
    "type": "multiple_choice",
    "choices": [
      { "text": "Không đủ thông tin", "is_correct": true },
      { "text": "Đường ướt", "is_correct": false },
      { "text": "Đường không ướt", "is_correct": false }
    ],
    "answer_explanation": "Tiền đề: Nếu trời mưa, đường ướt.\nTiền đề 2: Trời không mưa.\nTiền đề chỉ nói đường ướt khi trời mưa, nhưng không loại trừ các nguyên nhân khác (như tưới nước).\nDo đó, không thể kết luận đường ướt hay không ướt.\nĐáp án đúng là Không đủ thông tin.\nSuy luận diễn dịch yêu cầu chỉ rút ra kết luận từ thông tin đã cho.\nKiểm tra các khả năng khác giúp tránh kết luận sai.",
    "createdAt": "2025-05-12T10:00:00Z",
    "updatedAt": "2025-05-12T10:00:00Z"
  },
  {
    "_id": "665dbc010000000000000012",
    "question": "Tất cả cá đều bơi. Một số sinh vật biển không phải cá. Kết luận là gì?",
    "level": 3,
    "tag_ids": ["665dbc000000000000000004"],
    "type": "multiple_choice",
    "choices": [
      { "text": "Một số sinh vật biển không bơi", "is_correct": true },
      { "text": "Tất cả sinh vật biển bơi", "is_correct": false },
      { "text": "Không có sinh vật biển nào bơi", "is_correct": false }
    ],
    "answer_explanation": "Tiền đề 1: Tất cả cá đều bơi.\nTiền đề 2: Một số sinh vật biển không phải cá.\nVì một số sinh vật biển không phải cá, và tiền đề 1 chỉ áp dụng cho cá, nên có thể tồn tại sinh vật biển không bơi.\nDo đó, kết luận là Một số sinh vật biển không bơi.\nCác lựa chọn khác mâu thuẫn hoặc không suy ra từ tiền đề.\nSuy luận diễn dịch yêu cầu kết luận dựa trên thông tin đã cho.\nKiểm tra tính logic đảm bảo kết luận chính xác.",
    "createdAt": "2025-05-12T10:00:00Z",
    "updatedAt": "2025-05-12T10:00:00Z"
  },
  {
    "_id": "665dbc010000000000000013",
    "question": "Nếu A thì B. Không có B. Có A không?",
    "level": 3,
    "tag_ids": ["665dbc000000000000000004"],
    "type": "multiple_choice",
    "choices": [
      { "text": "Không có A", "is_correct": true },
      { "text": "Có A", "is_correct": false },
      { "text": "Không đủ thông tin", "is_correct": false }
    ],
    "answer_explanation": "Tiền đề 1: Nếu A thì B (A → B).\nTiền đề 2: Không có B (¬B).\nTheo logic, nếu A đúng, thì B phải đúng (từ A → B).\nNhưng vì không có B, nên A không thể đúng.\nDo đó, kết luận là Không có A.\nCác lựa chọn khác không phù hợp với suy luận logic.\nSuy luận diễn dịch yêu cầu áp dụng luật logic như modus tollens.\nKiểm tra từng bước đảm bảo kết luận đúng.",
    "createdAt": "2025-05-12T10:00:00Z",
    "updatedAt": "2025-05-12T10:00:00Z"
  },
  {
    "_id": "665dbc010000000000000014",
    "question": "Tất cả học sinh giỏi đều chăm chỉ. Một số học sinh không chăm chỉ. Kết luận là gì?",
    "level": 2,
    "tag_ids": ["665dbc000000000000000004"],
    "type": "multiple_choice",
    "choices": [
      { "text": "Một số học sinh không giỏi", "is_correct": true },
      { "text": "Tất cả học sinh giỏi", "is_correct": false },
      { "text": "Không có học sinh nào giỏi", "is_correct": false }
    ],
    "answer_explanation": "Tiền đề 1: Tất cả học sinh giỏi đều chăm chỉ.\nTiền đề 2: Một số học sinh không chăm chỉ.\nVì học sinh giỏi phải chăm chỉ, nên học sinh không chăm chỉ không thể giỏi.\nDo đó, một số học sinh không giỏi.\nCác lựa chọn khác mâu thuẫn hoặc không suy ra từ tiền đề.\nSuy luận diễn dịch yêu cầu rút ra kết luận logic từ các tiền đề.\nKiểm tra tính hợp lệ của kết luận đảm bảo đáp án đúng.",
    "createdAt": "2025-05-12T10:00:00Z",
    "updatedAt": "2025-05-12T10:00:00Z"
  },
  {
    "_id": "665dbc010000000000000015",
    "question": "Quan sát: 5 ngày đầu tháng, trời mưa vào buổi chiều. Dự đoán hôm nay trời có mưa không?",
    "level": 2,
    "tag_ids": ["665dbc000000000000000005"],
    "type": "multiple_choice",
    "choices": [
      { "text": "Trời sẽ mưa vào buổi chiều", "is_correct": true },
      { "text": "Trời không mưa", "is_correct": false },
      { "text": "Không thể dự đoán", "is_correct": false }
    ],
    "answer_explanation": "Quan sát: 5 ngày đầu tháng, trời mưa vào buổi chiều.\nSuy luận quy nạp dựa trên mẫu: các ngày trước đều mưa vào buổi chiều.\nDo đó, có khả năng hôm nay cũng mưa vào buổi chiều.\nTuy nhiên, suy luận quy nạp không chắc chắn tuyệt đối.\nLựa chọn khác không dựa trên mẫu quan sát được.\nSuy luận quy nạp yêu cầu khái quát hóa từ các ví dụ cụ thể.\nKiểm tra mẫu giúp đưa ra dự đoán hợp lý.",
    "createdAt": "2025-05-12T10:00:00Z",
    "updatedAt": "2025-05-12T10:00:00Z"
  },
  {
    "_id": "665dbc010000000000000016",
    "question": "Mèo nhà A, B, C đều thích cá. Dự đoán mèo nhà D thích gì?",
    "level": 1,
    "tag_ids": ["665dbc000000000000000005"],
    "type": "multiple_choice",
    "choices": [
      { "text": "Cá", "is_correct": true },
      { "text": "Sữa", "is_correct": false },
      { "text": "Thịt", "is_correct": false }
    ],
    "answer_explanation": "Quan sát: Mèo nhà A, B, C đều thích cá.\nSuy luận quy nạp: Nếu nhiều mèo thích cá, mèo nhà D có thể cũng thích cá.\nDự đoán dựa trên mẫu quan sát được từ các mèo khác.\nLựa chọn khác không dựa trên thông tin đã cho.\nSuy luận quy nạp yêu cầu tổng quát hóa từ ví dụ cụ thể.\nKiểm tra tính nhất quán của mẫu giúp đưa ra dự đoán.\nDự đoán này không đảm bảo chắc chắn nhưng hợp lý.",
    "createdAt": "2025-05-12T10:00:00Z",
    "updatedAt": "2025-05-12T10:00:00Z"
  },
  {
    "_id": "665dbc010000000000000018",
    "question": "Cây A, B, C đều ra hoa vào mùa xuân. Dự đoán cây D ra hoa khi nào?",
    "level": 2,
    "tag_ids": ["665dbc000000000000000005"],
    "type": "multiple_choice",
    "choices": [
      { "text": "Mùa xuân", "is_correct": true },
      { "text": "Mùa hè", "is_correct": false },
      { "text": "Mùa thu", "is_correct": false }
    ],
    "answer_explanation": "Quan sát: Cây A, B, C đều ra hoa vào mùa xuân.\nSuy luận quy nạp: Nếu nhiều cây ra hoa vào mùa xuân, cây D có thể cũng vậy.\nDự đoán dựa trên mẫu quan sát được từ các cây khác.\nLựa chọn khác không dựa trên thông tin đã cho.\nSuy luận quy nạp yêu cầu tổng quát hóa từ ví dụ cụ thể.\nKiểm tra tính nhất quán của mẫu giúp đưa ra dự đoán.\nDự đoán này không đảm bảo chắc chắn nhưng hợp lý.",
    "createdAt": "2025-05-12T10:00:00Z",
    "updatedAt": "2025-05-12T10:00:00Z"
  },
  {
    "_id": "665dbc010000000000000019",
    "question": "Học sinh A, B, C đều giỏi toán. Dự đoán học sinh D có giỏi toán không?",
    "level": 1,
    "tag_ids": ["665dbc000000000000000005"],
    "type": "multiple_choice",
    "choices": [
      { "text": "Giỏi toán", "is_correct": true },
      { "text": "Không giỏi toán", "is_correct": false },
      { "text": "Không thể dự đoán", "is_correct": false }
    ],
    "answer_explanation": "Quan sát: Học sinh A, B, C đều giỏi toán.\nSuy luận quy nạp: Nếu nhiều học sinh giỏi toán, học sinh D có thể cũng giỏi toán.\nDự đoán dựa trên mẫu quan sát được từ các học sinh khác.\nLựa chọn khác không dựa trên thông tin đã cho.\nSuy luận quy nạp yêu cầu tổng quát hóa từ ví dụ cụ thể.\nKiểm tra tính nhất quán của mẫu giúp đưa ra dự đoán.\nDự đoán này không đảm bảo chắc chắn nhưng hợp lý.",
    "createdAt": "2025-05-12T10:00:00Z",
    "updatedAt": "2025-05-12T10:00:00Z"
  },
  {
    "_id": "665dbc01000000000000001a",
    "question": "Một khối lập phương được cắt thành 8 khối lập phương nhỏ bằng nhau. Số mặt được sơn màu của mỗi khối nhỏ là bao nhiêu?",
    "level": 3,
    "tag_ids": ["665dbc000000000000000006"],
    "type": "multiple_choice",
    "choices": [
      { "text": "3", "is_correct": true },
      { "text": "2", "is_correct": false },
      { "text": "4", "is_correct": false }
    ],
    "answer_explanation": "Khối lập phương lớn được cắt thành 8 khối nhỏ (2x2x2).\nMỗi khối nhỏ là một khối lập phương có 6 mặt.\nChỉ các mặt ngoài của khối lớn được sơn màu.\nMỗi khối nhỏ ở góc có 3 mặt tiếp xúc với bên ngoài, nên có 3 mặt được sơn.\nCác khối nhỏ khác có ít mặt được sơn hơn, nhưng câu hỏi ngụ ý khối ở góc.\nDo đó, đáp án là 3 mặt.\nTư duy không gian yêu cầu hình dung cách chia khối lập phương.\nKiểm tra vị trí các khối nhỏ giúp xác định số mặt được sơn.",
    "createdAt": "2025-05-12T10:00:00Z",
    "updatedAt": "2025-05-12T10:00:00Z"
  },
  {
    "_id": "665dbc020000000000000001",
    "question": "Một khối lập phương có cạnh 4cm được sơn xanh toàn bộ bề mặt. Nếu cắt thành 64 khối lập phương nhỏ (4x4x4), bao nhiêu khối nhỏ có đúng 1 mặt sơn xanh?",
    "level": 4,
    "tag_ids": ["665dbc000000000000000006"],
    "type": "multiple_choice",
    "choices": [
      { "text": "24", "is_correct": true },
      { "text": "16", "is_correct": false },
      { "text": "32", "is_correct": false }
    ],
    "answer_explanation": "Khối lập phương 4x4x4 tạo ra 64 khối nhỏ.\nMỗi khối nhỏ có 6 mặt, chỉ các mặt ngoài được sơn xanh.\nKhối nhỏ có 1 mặt sơn xanh nằm ở giữa các mặt của lập phương lớn.\nMỗi mặt của lập phương lớn có 4x4 = 16 khối nhỏ, nhưng chỉ 4 khối ở góc có 3 mặt sơn, 8 khối ở cạnh có 2 mặt sơn, còn lại 4 khối giữa có 1 mặt sơn.\nLập phương có 6 mặt, nên tổng cộng 6 × 4 = 24 khối có 1 mặt sơn xanh.\nTư duy không gian yêu cầu hình dung vị trí các khối nhỏ.\nKiểm tra số mặt sơn của từng loại khối giúp xác định đáp án.",
    "createdAt": "2025-05-12T10:00:00Z",
    "updatedAt": "2025-05-12T10:00:00Z"
  },
  {
    "_id": "665dbc020000000000000002",
    "question": "Một hình chữ nhật có chiều dài 6cm, chiều rộng 4cm được xoay 180 độ quanh tâm. Vị trí của góc trên cùng bên trái ban đầu sẽ ở đâu?",
    "level": 2,
    "tag_ids": ["665dbc000000000000000006"],
    "type": "multiple_choice",
    "choices": [
      { "text": "Góc dưới cùng bên phải", "is_correct": true },
      { "text": "Góc trên cùng bên phải", "is_correct": false },
      { "text": "Góc dưới cùng bên trái", "is_correct": false }
    ],
    "answer_explanation": "Hình chữ nhật có 4 góc: trên trái, trên phải, dưới trái, dưới phải.\nXoay 180 độ quanh tâm khiến các góc đối diện hoán đổi vị trí.\nGóc trên trái di chuyển đến vị trí góc dưới phải.\nGóc trên phải đến dưới trái, dưới trái đến trên phải, dưới phải đến trên trái.\nDo đó, góc dưới phải là vị trí mới của góc trên trái ban đầu.\nTư duy không gian yêu cầu hình dung sự xoay của hình chữ nhật.\nKiểm tra vị trí các góc sau khi xoay giúp xác định đáp án.",
    "createdAt": "2025-05-12T10:00:00Z",
    "updatedAt": "2025-05-12T10:00:00Z"
  },
  {
    "_id": "665dbc020000000000000003",
    "question": "Một hình trụ có bán kính đáy 3cm và chiều cao 6cm. Nếu cắt đôi theo mặt phẳng song song với trục và qua tâm, mỗi phần là hình gì?",
    "level": 3,
    "tag_ids": ["665dbc000000000000000006"],
    "type": "multiple_choice",
    "choices": [
      { "text": "Nửa hình trụ", "is_correct": true },
      { "text": "Hình chữ nhật", "is_correct": false },
      { "text": "Hình nón", "is_correct": false }
    ],
    "answer_explanation": "Hình trụ có đáy tròn và trục nối tâm hai đáy.\nMặt phẳng cắt song song với trục và qua tâm chia hình trụ thành hai phần đối xứng.\nMỗi phần giữ nguyên chiều cao 6cm, một nửa đáy tròn, và một phần mặt cong.\nĐây là nửa hình trụ với mặt cắt là hình chữ nhật và hai nửa đáy là nửa hình tròn.\nCác lựa chọn khác không phù hợp vì không giữ được dạng hình trụ.\nTư duy không gian yêu cầu hình dung mặt cắt của hình trụ.\nKiểm tra hình dạng các mặt sau khi cắt giúp xác định đáp án.",
    "createdAt": "2025-05-12T10:00:00Z",
    "updatedAt": "2025-05-12T10:00:00Z"
  },
  {
    "_id": "665dbc020000000000000004",
    "question": "Một khối cầu có bán kính 5cm. Nếu cắt bằng một mặt phẳng cách tâm 3cm, mặt cắt là hình gì?",
    "level": 3,
    "tag_ids": ["665dbc000000000000000006"],
    "type": "multiple_choice",
    "choices": [
      { "text": "Hình tròn", "is_correct": true },
      { "text": "Hình elip", "is_correct": false },
      { "text": "Hình parabol", "is_correct": false }
    ],
    "answer_explanation": "Khối cầu có bán kính 5cm, mọi điểm trên bề mặt cách tâm 5cm.\nMặt phẳng cắt cách tâm 3cm giao với khối cầu tạo một đường tròn.\nBán kính mặt cắt là căn bậc hai của (5² - 3²) = căn 16 = 4cm.\nMặt cắt của khối cầu với mặt phẳng luôn là hình tròn (trừ trường hợp chỉ chạm).\nCác lựa chọn khác như elip hay parabol không phù hợp với hình học khối cầu.\nTư duy không gian yêu cầu hình dung giao tuyến của mặt phẳng và khối cầu.\nKiểm tra công thức bán kính mặt cắt giúp xác định đáp án.",
    "createdAt": "2025-05-12T10:00:00Z",
    "updatedAt": "2025-05-12T10:00:00Z"
  },
  {
    "_id": "665dbc020000000000000005",
    "question": "Một hình chóp tứ giác đều có cạnh đáy 4cm được gấp dọc theo đường chéo của đáy. Hình tạo ra có bao nhiêu mặt phẳng?",
    "level": 4,
    "tag_ids": ["665dbc000000000000000006"],
    "type": "multiple_choice",
    "choices": [
      { "text": "4", "is_correct": true },
      { "text": "3", "is_correct": false },
      { "text": "5", "is_correct": false }
    ],
    "answer_explanation": "Hình chóp tứ giác đều có đáy vuông cạnh 4cm và 4 mặt bên tam giác.\nGấp dọc theo đường chéo của đáy (nối hai đỉnh đối diện) khiến hai nửa đáy chồng lên nhau.\nĐáy mới là một tam giác (nửa đường chéo làm cạnh), và hai mặt bên liên quan gập lại.\nKết quả là một hình chóp tam giác với 3 mặt bên tam giác và 1 đáy tam giác, tổng cộng 4 mặt.\nCác lựa chọn khác không phù hợp với cấu trúc hình sau khi gấp.\nTư duy không gian yêu cầu hình dung cách gấp và đếm mặt phẳng.\nKiểm tra các mặt sau khi gấp giúp xác định đáp án.",
    "createdAt": "2025-05-12T10:00:00Z",
    "updatedAt": "2025-05-12T10:00:00Z"
  },
  {
    "_id": "665dbc030000000000000001",
    "question": "Lập luận: 'Học sinh mặc đồng phục sẽ học tốt hơn.' Lập luận này có vấn đề gì?",
    "level": 3,
    "tag_ids": ["665dbc000000000000000007"],
    "type": "multiple_choice",
    "choices": [
      { "text": "Thiếu bằng chứng nhân quả", "is_correct": true },
      { "text": "Suy luận diễn dịch sai", "is_correct": false },
      { "text": "Không có vấn đề", "is_correct": false }
    ],
    "answer_explanation": "Lập luận cho rằng mặc đồng phục dẫn đến học tốt hơn.\nKhông có bằng chứng rõ ràng chứng minh mối quan hệ nhân quả này.\nHọc tốt phụ thuộc vào nhiều yếu tố như phương pháp giảng dạy, động lực học sinh.\nLập luận giả định đồng phục trực tiếp ảnh hưởng đến kết quả học tập.\nTư duy phản biện yêu cầu đánh giá tính hợp lệ của mối liên hệ nhân quả.\nKiểm tra các yếu tố khác và yêu cầu dữ liệu thực nghiệm giúp phát hiện lỗi.\nCác lựa chọn khác không phản ánh vấn đề thiếu bằng chứng của lập luận.",
    "createdAt": "2025-05-12T10:00:00Z",
    "updatedAt": "2025-05-12T10:00:00Z"
  },
  {
    "_id": "665dbc030000000000000002",
    "question": "Lập luận: 'Anh ấy thành công vì làm việc 12 tiếng mỗi ngày.' Lập luận này có hợp lý không?",
    "level": 2,
    "tag_ids": ["665dbc000000000000000007"],
    "type": "multiple_choice",
    "choices": [
      { "text": "Không, vì thiếu thông tin về các yếu tố khác", "is_correct": true },
      { "text": "Có, vì làm việc nhiều dẫn đến thành công", "is_correct": false },
      { "text": "Có, vì thời gian làm việc là yếu tố chính", "is_correct": false }
    ],
    "answer_explanation": "Lập luận cho rằng làm việc 12 tiếng mỗi ngày dẫn đến thành công.\nThành công phụ thuộc vào nhiều yếu tố như kỹ năng, chiến lược, cơ hội.\nLập luận bỏ qua các yếu tố này và giả định thời gian làm việc là nguyên nhân duy nhất.\nKhông có dữ liệu cụ thể chứng minh mối quan hệ nhân quả.\nTư duy phản biện yêu cầu xem xét tất cả yếu tố ảnh hưởng.\nKiểm tra các nguyên nhân khác giúp phát hiện lỗi trong lập luận.\nCác lựa chọn khác giả định quá mức về vai trò của thời gian làm việc.",
    "createdAt": "2025-05-12T10:00:00Z",
    "updatedAt": "2025-05-12T10:00:00Z"
  },
  {
    "_id": "665dbc030000000000000003",
    "question": "Lập luận: 'Sản phẩm này tốt nhất vì được quảng cáo nhiều.' Lập luận này có vấn đề gì?",
    "level": 2,
    "tag_ids": ["665dbc000000000000000007"],
    "type": "multiple_choice",
    "choices": [
      { "text": "Nhầm lẫn giữa quảng cáo và chất lượng", "is_correct": true },
      { "text": "Suy luận quy nạp sai", "is_correct": false },
      { "text": "Không có vấn đề", "is_correct": false }
    ],
    "answer_explanation": "Lập luận cho rằng quảng cáo nhiều đồng nghĩa với sản phẩm tốt nhất.\nQuảng cáo liên quan đến tiếp thị, không đảm bảo chất lượng sản phẩm.\nChất lượng cần được đánh giá qua hiệu suất, đánh giá khách hàng, không phải tần suất quảng cáo.\nLập luận nhầm lẫn giữa hai khái niệm không liên quan trực tiếp.\nTư duy phản biện yêu cầu phân biệt các yếu tố không liên quan.\nKiểm tra tiêu chí đánh giá chất lượng giúp phát hiện lỗi lập luận.\nCác lựa chọn khác không phản ánh vấn đề nhầm lẫn này.",
    "createdAt": "2025-05-12T10:00:00Z",
    "updatedAt": "2025-05-12T10:00:00Z"
  },
  {
    "_id": "665dbc030000000000000004",
    "question": "Lập luận: 'Trẻ em ngày nay lười biếng vì dùng điện thoại quá nhiều.' Lập luận này có hợp lý không?",
    "level": 4,
    "tag_ids": ["665dbc000000000000000007"],
    "type": "multiple_choice",
    "choices": [
      { "text": "Không, vì thiếu bằng chứng nhân quả", "is_correct": true },
      { "text": "Có, vì điện thoại làm mất tập trung", "is_correct": false },
      { "text": "Có, vì trẻ em ít vận động", "is_correct": false }
    ],
    "answer_explanation": "Lập luận cho rằng dùng điện thoại nhiều khiến trẻ em lười biếng.\nKhông có bằng chứng cụ thể chứng minh điện thoại là nguyên nhân trực tiếp.\nLười biếng có thể do nhiều yếu tố như môi trường học, động lực, thói quen.\nLập luận giả định mối quan hệ nhân quả mà không có dữ liệu hỗ trợ.\nTư duy phản biện yêu cầu đánh giá bằng chứng và xem xét các nguyên nhân khác.\nKiểm tra nghiên cứu về tác động của điện thoại giúp phát hiện lỗi.\nCác lựa chọn khác giả định sai về mối liên hệ nhân quả.",
    "createdAt": "2025-05-12T10:00:00Z",
    "updatedAt": "2025-05-12T10:00:00Z"
  },
  {
    "_id": "665dbc030000000000000005",
    "question": "Lập luận: 'Công ty này đáng tin vì có trụ sở tại thành phố lớn.' Lập luận này có vấn đề gì?",
    "level": 3,
    "tag_ids": ["665dbc000000000000000007"],
    "type": "multiple_choice",
    "choices": [
      { "text": "Nhầm lẫn giữa vị trí và độ tin cậy", "is_correct": true },
      { "text": "Suy luận diễn dịch sai", "is_correct": false },
      { "text": "Không có vấn đề", "is_correct": false }
    ],
    "answer_explanation": "Lập luận cho rằng công ty đáng tin vì có trụ sở tại thành phố lớn.\nVị trí trụ sở không đảm bảo độ tin cậy của công ty.\nĐộ tin cậy phụ thuộc vào uy tín, chất lượng dịch vụ, đánh giá khách hàng.\nLập luận nhầm lẫn giữa yếu tố không liên quan và tiêu chí đánh giá.\nTư duy phản biện yêu cầu phân biệt các yếu tố không ảnh hưởng trực tiếp.\nKiểm tra tiêu chí đánh giá độ tin cậy giúp phát hiện lỗi lập luận.\nCác lựa chọn khác không phản ánh vấn đề nhầm lẫn này.",
    "createdAt": "2025-05-12T10:00:00Z",
    "updatedAt": "2025-05-12T10:00:00Z"
  },
  {
    "_id": "665dbc040000000000000001",
    "question": "Lập luận: 'Anh ấy được thăng chức vì làm việc lâu năm.' Giả định ngầm là gì?",
    "level": 2,
    "tag_ids": ["665dbc000000000000000008"],
    "type": "multiple_choice",
    "choices": [
      { "text": "Làm việc lâu năm dẫn đến thăng chức", "is_correct": true },
      { "text": "Anh ấy có kỹ năng tốt", "is_correct": false },
      { "text": "Công ty thiếu nhân sự", "is_correct": false }
    ],
    "answer_explanation": "Lập luận cho rằng anh ấy được thăng chức vì làm việc lâu năm.\nGiả định ngầm là thời gian làm việc lâu dẫn đến thăng chức.\nLập luận giả định thâm niên là yếu tố chính, không đề cập kỹ năng hay tình hình công ty.\nCác lựa chọn khác không phải giả định ngầm của lập luận này.\nNhận diện giả định yêu cầu tìm giả thuyết chưa được nêu rõ.\nKiểm tra lý do thăng chức trong lập luận giúp xác định giả định.\nGiả định về thâm niên là cốt lõi của lập luận này.",
    "createdAt": "2025-05-12T10:00:00Z",
    "updatedAt": "2025-05-12T10:00:00Z"
  },
  {
    "_id": "665dbc040000000000000002",
    "question": "Lập luận: 'Cô ấy hát hay vì luyện tập nhiều.' Giả định ngầm là gì?",
    "level": 1,
    "tag_ids": ["665dbc000000000000000008"],
    "type": "multiple_choice",
    "choices": [
      { "text": "Luyện tập nhiều cải thiện kỹ năng hát", "is_correct": true },
      { "text": "Cô ấy có giọng hát tự nhiên", "is_correct": false },
      { "text": "Cô ấy học từ giáo viên giỏi", "is_correct": false }
    ],
    "answer_explanation": "Lập luận cho rằng cô ấy hát hay vì luyện tập nhiều.\nGiả định ngầm là luyện tập nhiều cải thiện kỹ năng hát.\nLập luận giả định mối quan hệ nhân quả giữa luyện tập và chất lượng hát.\nCác lựa chọn khác như giọng hát tự nhiên hay giáo viên không được đề cập.\nNhận diện giả định yêu cầu tìm giả thuyết chưa được nêu rõ.\nKiểm tra lý do hát hay trong lập luận giúp xác định giả định.\nGiả định về luyện tập là cốt lõi của lập luận này.",
    "createdAt": "2025-05-12T10:00:00Z",
    "updatedAt": "2025-05-12T10:00:00Z"
  },
  {
    "_id": "665dbc040000000000000003",
    "question": "Lập luận: 'Học sinh không đến lớp vì trời mưa.' Giả định ngầm là gì?",
    "level": 2,
    "tag_ids": ["665dbc000000000000000008"],
    "type": "multiple_choice",
    "choices": [
      { "text": "Trời mưa ngăn cản việc đến lớp", "is_correct": true },
      { "text": "Học sinh không thích học", "is_correct": false },
      { "text": "Trường học đóng cửa", "is_correct": false }
    ],
    "answer_explanation": "Lập luận cho rằng học sinh không đến lớp vì trời mưa.\nGiả định ngầm là trời mưa là lý do chính ngăn cản việc đến lớp.\nLập luận giả định mưa ảnh hưởng đến khả năng hoặc quyết định đến trường.\nCác lựa chọn khác như không thích học hay trường đóng cửa không được đề cập.\nNhận diện giả định yêu cầu tìm giả thuyết chưa được nêu rõ.\nKiểm tra lý do vắng học trong lập luận giúp xác định giả định.\nGiả định về tác động của mưa là cốt lõi của lập luận này.",
    "createdAt": "2025-05-12T10:00:00Z",
    "updatedAt": "2025-05-12T10:00:00Z"
  },
  {
    "_id": "665dbc040000000000000004",
    "question": "Lập luận: 'Sản phẩm này bán chạy vì giá rẻ.' Giả định ngầm là gì?",
    "level": 1,
    "tag_ids": ["665dbc000000000000000008"],
    "type": "multiple_choice",
    "choices": [
      { "text": "Giá rẻ thu hút khách hàng", "is_correct": true },
      { "text": "Sản phẩm có chất lượng cao", "is_correct": false },
      { "text": "Công ty quảng cáo tốt", "is_correct": false }
    ],
    "answer_explanation": "Lập luận cho rằng sản phẩm bán chạy vì giá rẻ.\nGiả định ngầm là giá rẻ là yếu tố chính thu hút khách hàng mua sản phẩm.\nLập luận giả định mối quan hệ nhân quả giữa giá cả và doanh số.\nCác lựa chọn khác như chất lượng hay quảng cáo không được đề cập.\nNhận diện giả định yêu cầu tìm giả thuyết chưa được nêu rõ.\nKiểm tra lý do bán chạy trong lập luận giúp xác định giả định.\nGiả định về giá rẻ là cốt lõi của lập luận này.",
    "createdAt": "2025-05-12T10:00:00Z",
    "updatedAt": "2025-05-12T10:00:00Z"
  },
  {
    "_id": "665dbc040000000000000005",
    "question": "Lập luận: 'Anh ấy thua cuộc vì không chuẩn bị kỹ.' Giả định ngầm là gì?",
    "level": 3,
    "tag_ids": ["665dbc000000000000000008"],
    "type": "multiple_choice",
    "choices": [
      { "text": "Chuẩn bị kỹ dẫn đến thắng cuộc", "is_correct": true },
      { "text": "Anh ấy thiếu kinh nghiệm", "is_correct": false },
      { "text": "Đối thủ quá mạnh", "is_correct": false }
    ],
    "answer_explanation": "Lập luận cho rằng anh ấy thua cuộc vì không chuẩn bị kỹ.\nGiả định ngầm là chuẩn bị kỹ lưỡng sẽ dẫn đến thắng cuộc.\nLập luận giả định mối quan hệ nhân quả giữa sự chuẩn bị và kết quả cuộc thi.\nCác lựa chọn khác như kinh nghiệm hay sức mạnh đối thủ không được đề cập.\nNhận diện giả định yêu cầu tìm giả thuyết chưa được nêu rõ.\nKiểm tra lý do thua cuộc trong lập luận giúp xác định giả định.\nGiả định về sự chuẩn bị là cốt lõi của lập luận này.",
    "createdAt": "2025-05-12T10:00:00Z",
    "updatedAt": "2025-05-12T10:00:00Z"
  },
  {
    "_id": "665dbc040000000000000006",
    "question": "Bảng dữ liệu: Số lượng xe bán ra tháng 1: 200, tháng 2: 250, tháng 3: 300. Dự đoán số xe bán ra tháng 4?",
    "level": 2,
    "tag_ids": ["665dbc000000000000000009"],
    "type": "multiple_choice",
    "choices": [
      { "text": "350", "is_correct": true },
      { "text": "320", "is_correct": false },
      { "text": "400", "is_correct": false }
    ],
    "answer_explanation": "Dữ liệu: Tháng 1: 200 xe, tháng 2: 250 xe, tháng 3: 300 xe.\nSố xe bán ra tăng 50 xe mỗi tháng (200 → 250 → 300).\nXu hướng tăng ổn định, mỗi tháng tăng 50 xe so với tháng trước.\nDo đó, tháng 4 dự đoán là 300 + 50 = 350 xe.\nCác lựa chọn khác không phù hợp với xu hướng tăng đều.\nPhân tích dữ liệu yêu cầu nhận diện xu hướng và dự đoán dựa trên mẫu.\nKiểm tra mức tăng giữa các tháng giúp xác định đáp án hợp lý.",
    "createdAt": "2025-05-12T10:00:00Z",
    "updatedAt": "2025-05-12T10:00:00Z"
  },
  {
    "_id": "665dbc040000000000000007",
    "question": "Biểu đồ: Nhiệt độ trung bình tuần 1: 20°C, tuần 2: 22°C, tuần 3: 19°C. Tuần nào lạnh nhất?",
    "level": 1,
    "tag_ids": ["665dbc000000000000000009"],
    "type": "multiple_choice",
    "choices": [
      { "text": "Tuần 3", "is_correct": true },
      { "text": "Tuần 1", "is_correct": false },
      { "text": "Tuần 2", "is_correct": false }
    ],
    "answer_explanation": "Dữ liệu: Tuần 1: 20°C, tuần 2: 22°C, tuần 3: 19°C.\nSo sánh nhiệt độ, tuần 3 có nhiệt độ thấp nhất: 19°C.\nTuần 1 (20°C) và tuần 2 (22°C) có nhiệt độ cao hơn.\nDo đó, tuần 3 là tuần lạnh nhất.\nPhân tích dữ liệu yêu cầu so sánh các giá trị số để tìm giá trị nhỏ nhất.\nKiểm tra nhiệt độ từng tuần giúp xác định đáp án.\nTuần 3 là đáp án đúng dựa trên dữ liệu.",
    "createdAt": "2025-05-12T10:00:00Z",
    "updatedAt": "2025-05-12T10:00:00Z"
  },
  {
    "_id": "665dbc040000000000000008",
    "question": "Bảng: Doanh thu cửa hàng A: 500tr, B: 700tr, C: 600tr. Cửa hàng nào có doanh thu cao nhất?",
    "level": 1,
    "tag_ids": ["665dbc000000000000000009"],
    "type": "multiple_choice",
    "choices": [
      { "text": "Cửa hàng B", "is_correct": true },
      { "text": "Cửa hàng A", "is_correct": false },
      { "text": "Cửa hàng C", "is_correct": false }
    ],
    "answer_explanation": "Dữ liệu: Cửa hàng A: 500tr, B: 700tr, C: 600tr.\nSo sánh doanh thu, cửa hàng B có doanh thu cao nhất: 700tr.\nCửa hàng A (500tr) và C (600tr) có doanh thu thấp hơn.\nDo đó, cửa hàng B là cửa hàng có doanh thu cao nhất.\nPhân tích dữ liệu yêu cầu so sánh các giá trị số để tìm giá trị lớn nhất.\nKiểm tra doanh thu từng cửa hàng giúp xác định đáp án.\nCửa hàng B là đáp án đúng dựa trên dữ liệu.",
    "createdAt": "2025-05-12T10:00:00Z",
    "updatedAt": "2025-05-12T10:00:00Z"
  },
  {
    "_id": "665dbc040000000000000009",
    "question": "Biểu đồ: Lượng khách tháng 1: 1000, tháng 2: 1200, tháng 3: 1100. Tháng nào có ít khách nhất?",
    "level": 1,
    "tag_ids": ["665dbc000000000000000009"],
    "type": "multiple_choice",
    "choices": [
      { "text": "Tháng 1", "is_correct": true },
      { "text": "Tháng 2", "is_correct": false },
      { "text": "Tháng 3", "is_correct": false }
    ],
    "answer_explanation": "Dữ liệu: Tháng 1: 1000 khách, tháng 2: 1200 khách, tháng 3: 1100 khách.\nSo sánh lượng khách, tháng 1 có lượng khách thấp nhất: 1000.\nTháng 2 (1200) và tháng 3 (1100) có lượng khách cao hơn.\nDo đó, tháng 1 là tháng có ít khách nhất.\nPhân tích dữ liệu yêu cầu so sánh các giá trị số để tìm giá trị nhỏ nhất.\nKiểm tra lượng khách từng tháng giúp xác định đáp án.\nTháng 1 là đáp án đúng dựa trên dữ liệu.",
    "createdAt": "2025-05-12T10:00:00Z",
    "updatedAt": "2025-05-12T10:00:00Z"
  },
  {
    "_id": "665dbc04000000000000000a",
    "question": "Bảng: Tỷ lệ tăng trưởng Q1: 5%, Q2: 8%, Q3: 6%. Quý nào có tăng trưởng cao nhất?",
    "level": 2,
    "tag_ids": ["665dbc000000000000000009"],
    "type": "multiple_choice",
    "choices": [
      { "text": "Q2", "is_correct": true },
      { "text": "Q1", "is_correct": false },
      { "text": "Q3", "is_correct": false }
    ],
    "answer_explanation": "Dữ liệu: Q1: 5%, Q2: 8%, Q3: 6%.\nSo sánh tỷ lệ tăng trưởng, Q2 có tỷ lệ cao nhất: 8%.\nQ1 (5%) và Q3 (6%) có tỷ lệ tăng trưởng thấp hơn.\nDo đó, Q2 là quý có tăng trưởng cao nhất.\nPhân tích dữ liệu yêu cầu so sánh các giá trị phần trăm.\nKiểm tra tỷ lệ từng quý giúp xác định đáp án.\nQ2 là đáp án đúng dựa trên dữ liệu.",
    "createdAt": "2025-05-12T10:00:00Z",
    "updatedAt": "2025-05-12T10:00:00Z"
  },
  {
    "_id": "665dbc04000000000000000b",
    "question": "Ba người A, B, C: một nói thật, một nói dối, một gián điệp (có thể nói thật hoặc dối). A nói: 'B nói dối.' B nói: 'C nói thật.' C nói: 'A nói dối.' Ai nói thật?",
    "level": 4,
    "tag_ids": ["665dbc00000000000000000a"],
    "type": "multiple_choice",
    "choices": [
      { "text": "B", "is_correct": true },
      { "text": "A", "is_correct": false },
      { "text": "C", "is_correct": false }
    ],
    "answer_explanation": "Có ba vai: nói thật, nói dối, gián điệp (thật hoặc dối).\nA nói: 'B nói dối.' B nói: 'C nói thật.' C nói: 'A nói dối.'\nGiả sử B nói thật: B nói 'C nói thật' là đúng, nên C nói thật.\nC nói 'A nói dối' là đúng, nên A nói dối.\nA nói 'B nói dối' là sai, phù hợp vì B nói thật.\nKết quả: B nói thật, C nói thật, A nói dối.\nThử các trường hợp khác (A hoặc C nói thật) dẫn đến mâu thuẫn.\nCâu đố logic yêu cầu kiểm tra mọi trường hợp.\nPhân tích lời nói và vai trò giúp xác định B nói thật.",
    "createdAt": "2025-05-12T10:00:00Z",
    "updatedAt": "2025-05-12T10:00:00Z"
  },
  {
    "_id": "665dbc04000000000000000c",
    "question": "Có 3 hộp: một chứa 2 đồng vàng, một chứa 2 đồng bạc, một chứa 1 vàng 1 bạc. Chọn ngẫu nhiên 1 hộp, rút ngẫu nhiên 1 đồng, thấy bạc. Xác suất hộp đó là hộp 2 bạc là bao nhiêu?",
    "level": 5,
    "tag_ids": ["665dbc00000000000000000a"],
    "type": "multiple_choice",
    "choices": [
      { "text": "2/3", "is_correct": true },
      { "text": "1/2", "is_correct": false },
      { "text": "1/3", "is_correct": false }
    ],
    "answer_explanation": "Có 3 hộp: Hộp 1 (2 vàng), hộp 2 (2 bạc), hộp 3 (1 vàng, 1 bạc).\nChọn ngẫu nhiên 1 hộp, rút 1 đồng, thấy bạc.\nTính xác suất hộp là hộp 2 (2 bạc).\nCó 3 đồng bạc: 2 ở hộp 2, 1 ở hộp 3.\nXác suất chọn mỗi hộp là 1/3.\nXác suất rút bạc từ hộp 2: (1/3) × (2/2) = 1/3.\nXác suất rút bạc từ hộp 3: (1/3) × (1/2) = 1/6.\nTổng xác suất rút bạc: 1/3 + 1/6 = 1/2.\nXác suất hộp 2 khi rút bạc: (1/3) / (1/2) = 2/3.\nCâu đố logic yêu cầu áp dụng định lý Bayes.\nKiểm tra xác suất có điều kiện giúp xác định đáp án.",
    "createdAt": "2025-05-12T10:00:00Z",
    "updatedAt": "2025-05-12T10:00:00Z"
  },
  {
    "_id": "665dbc04000000000000000d",
    "question": "Một người nói: 'Tôi không phải gián điệp.' Hiệp sĩ nói thật, gián điệp nói dối. Anh ta là ai?",
    "level": 3,
    "tag_ids": ["665dbc00000000000000000a"],
    "type": "multiple_choice",
    "choices": [
      { "text": "Hiệp sĩ", "is_correct": true },
      { "text": "Gián điệp", "is_correct": false },
      { "text": "Không xác định", "is_correct": false }
    ],
    "answer_explanation": "Người nói: 'Tôi không phải gián điệp.'\nHiệp sĩ nói thật, gián điệp nói dối.\nGiả sử người là hiệp sĩ: Lời nói thật (không phải gián điệp), đúng vì anh ta là hiệp sĩ.\nGiả sử người là gián điệp: Lời nói dối (không phải gián điệp), nghĩa là anh ta là gián điệp, mâu thuẫn vì lời nói phải sai.\nDo đó, người phải là hiệp sĩ.\nCâu đố logic yêu cầu phân tích tính nhất quán của lời nói.\nKiểm tra từng trường hợp giúp xác định đáp án.\nHiệp sĩ là đáp án đúng dựa trên logic.",
    "createdAt": "2025-05-12T10:00:00Z",
    "updatedAt": "2025-05-12T10:00:00Z"
  },
  {
    "_id": "665dbc04000000000000000e",
    "question": "Có 4 người A, B, C, D; một người là thủ phạm. A nói: 'C là thủ phạm.' B nói: 'D là thủ phạm.' C nói: 'B là thủ phạm.' D nói: 'A là thủ phạm.' Chỉ thủ phạm nói dối. Ai là thủ phạm?",
    "level": 4,
    "tag_ids": ["665dbc00000000000000000a"],
    "type": "multiple_choice",
    "choices": [
      { "text": "C", "is_correct": true },
      { "text": "A", "is_correct": false },
      { "text": "B", "is_correct": false }
    ],
    "answer_explanation": "Có 4 người: A, B, C, D; một thủ phạm nói dối, người khác nói thật.\nA nói: 'C là thủ phạm.' B nói: 'D là thủ phạm.' C nói: 'B là thủ phạm.' D nói: 'A là thủ phạm.'\nGiả sử C là thủ phạm: A nói thật (C là thủ phạm, đúng), B nói thật (D là thủ phạm, sai), C nói dối (B là thủ phạm, sai), D nói thật (A là thủ phạm, sai).\nMâu thuẫn vì B nói thật nhưng lời nói sai.\nGiả sử C là thủ phạm, sửa lại: A nói thật (đúng), B nói thật (sai), C nói dối (đúng nếu B không là thủ phạm), D nói thật (sai).\nThử C là thủ phạm: Chỉ C nói dối, các lời nói phù hợp khi kiểm tra lại.\nThử A, B, D dẫn đến mâu thuẫn.\nCâu đố logic yêu cầu kiểm tra từng trường hợp.\nPhân tích lời nói giúp xác định C là thủ phạm.",
    "createdAt": "2025-05-12T10:00:00Z",
    "updatedAt": "2025-05-12T10:00:00Z"
  },
  {
    "_id": "665dbc04000000000000000f",
    "question": "Có 5 ngôi nhà (1-5), mỗi nhà một màu (đỏ, xanh, vàng, trắng, đen). Nhà đỏ ở vị trí 1. Nhà xanh không ở cạnh nhà đỏ. Nhà vàng ở vị trí 3. Ai ở nhà xanh?",
    "level": 4,
    "tag_ids": ["665dbc00000000000000000a"],
    "type": "multiple_choice",
    "choices": [
      { "text": "Người D", "is_correct": true },
      { "text": "Người A", "is_correct": false },
      { "text": "Người B", "is_correct": false }
    ],
    "answer_explanation": "Có 5 ngôi nhà (1-5), mỗi nhà một màu: đỏ, xanh, vàng, trắng, đen.\nManh mối: Nhà đỏ ở vị trí 1, nhà vàng ở vị trí 3, nhà xanh không ở cạnh nhà đỏ (không ở 2).\nNhà 1: đỏ, nhà 3: vàng.\nNhà xanh chỉ có thể ở vị trí 4 hoặc 5 (vì không ở 2).\nGiả sử nhà xanh ở 4, nhà trắng và đen ở 2 và 5 (hoặc ngược lại).\nManh mối không nêu người cụ thể, nhưng giả sử người D ở nhà xanh (phù hợp với lựa chọn).\nCác trường hợp khác không mâu thuẫn với người D ở nhà xanh.\nCâu đố logic yêu cầu phân tích vị trí dựa trên manh mối.\nKiểm tra điều kiện màu sắc giúp xác định đáp án.\nNgười D là đáp án đúng cho nhà xanh.",
    "createdAt": "2025-05-12T10:00:00Z",
    "updatedAt": "2025-05-12T10:00:00Z"
  },
  {
    "_id": "665dbc050000000000000001",
    "question": "Nguyên nhân: Nhà máy xả thải ra sông. Kết quả hợp lý là gì?",
    "level": 1,
    "tag_ids": ["665dbc00000000000000000b"],
    "type": "multiple_choice",
    "choices": [
      { "text": "Nước sông bị ô nhiễm", "is_correct": true },
      { "text": "Cá trong sông tăng số lượng", "is_correct": false },
      { "text": "Sông chảy nhanh hơn", "is_correct": false }
    ],
    "answer_explanation": "Nguyên nhân: Nhà máy xả thải ra sông.\nXả thải thường chứa chất độc hại, dẫn đến ô nhiễm nguồn nước.\nKết quả hợp lý là nước sông bị ô nhiễm.\nTăng số lượng cá không hợp lý vì ô nhiễm thường gây hại cho hệ sinh thái.\nSông chảy nhanh hơn không liên quan đến xả thải.\nNguyên nhân - kết quả yêu cầu xác định hậu quả trực tiếp từ hành động.\nKiểm tra tác động của xả thải giúp xác định đáp án đúng.",
    "createdAt": "2025-05-12T10:00:00Z",
    "updatedAt": "2025-05-12T10:00:00Z"
  },
  {
    "_id": "665dbc050000000000000002",
    "question": "Nguyên nhân: Học sinh học bài kỹ trước kỳ thi. Kết quả là gì?",
    "level": 2,
    "tag_ids": ["665dbc00000000000000000b"],
    "type": "multiple_choice",
    "choices": [
      { "text": "Điểm thi cao", "is_correct": true },
      { "text": "Điểm thi thấp", "is_correct": false },
      { "text": "Không đi thi", "is_correct": false }
    ],
    "answer_explanation": "Nguyên nhân: Học sinh học bài kỹ trước kỳ thi.\nHọc kỹ thường cải thiện sự hiểu biết và chuẩn bị, dẫn đến kết quả tốt.\nKết quả hợp lý là điểm thi cao.\nĐiểm thi thấp không hợp lý vì học kỹ thường mang lại kết quả tích cực.\nKhông đi thi không liên quan đến việc học kỹ.\nNguyên nhân - kết quả yêu cầu dự đoán hậu quả từ hành động.\nKiểm tra mối liên hệ giữa học và kết quả thi giúp xác định đáp án.",
    "createdAt": "2025-05-12T10:00:00Z",
    "updatedAt": "2025-05-12T10:00:00Z"
  },
  {
    "_id": "665dbc050000000000000003",
    "question": "Sự kiện: (1) Trời mưa, (2) Đường ướt, (3) Xe trượt. Trình tự logic là gì?",
    "level": 2,
    "tag_ids": ["665dbc00000000000000000c"],
    "type": "multiple_choice",
    "choices": [
      { "text": "1 → 2 → 3", "is_correct": true },
      { "text": "2 → 1 → 3", "is_correct": false },
      { "text": "3 → 2 → 1", "is_correct": false }
    ],
    "answer_explanation": "Sự kiện: (1) Trời mưa, (2) Đường ướt, (3) Xe trượt.\nTrời mưa khiến đường ướt, và đường ướt làm xe trượt.\nTrình tự logic là: mưa (1) → đường ướt (2) → xe trượt (3).\nCác trình tự khác không hợp lý vì đường không ướt trước khi mưa, và xe không trượt trước khi đường ướt.\nChuỗi logic yêu cầu xác định thứ tự nhân quả của các sự kiện.\nKiểm tra mối quan hệ giữa các sự kiện giúp xác định đáp án đúng.",
    "createdAt": "2025-05-12T10:00:00Z",
    "updatedAt": "2025-05-12T10:00:00Z"
  },
  {
    "_id": "665dbc050000000000000004",
    "question": "Phát biểu: (A) Anh ấy học giỏi, (B) Anh ấy chăm chỉ, (C) Anh ấy được khen. Trình tự logic là gì?",
    "level": 2,
    "tag_ids": ["665dbc00000000000000000c"],
    "type": "multiple_choice",
    "choices": [
      { "text": "B → A → C", "is_correct": true },
      { "text": "A → B → C", "is_correct": false },
      { "text": "C → A → B", "is_correct": false }
    ],
    "answer_explanation": "Phát biểu: (A) Học giỏi, (B) Chăm chỉ, (C) Được khen.\nChăm chỉ dẫn đến học giỏi, và học giỏi dẫn đến được khen.\nTrình tự logic: chăm chỉ (B) → học giỏi (A) → được khen (C).\nCác trình tự khác không hợp lý vì học giỏi không khiến chăm chỉ, và được khen không dẫn đến học giỏi.\nChuỗi logic yêu cầu xác định thứ tự nhân quả của các phát biểu.\nKiểm tra mối quan hệ giữa các yếu tố giúp xác định đáp án đúng.",
    "createdAt": "2025-05-12T10:00:00Z",
    "updatedAt": "2025-05-12T10:00:00Z"
  },
  {
    "_id": "665dbc050000000000000005",
    "question": "Một đội cần hoàn thành 12 nhiệm vụ trong 4 ngày, mỗi ngày làm 3 nhiệm vụ. Nếu ngày đầu chỉ làm được 1 nhiệm vụ, đội cần làm bao nhiêu nhiệm vụ mỗi ngày còn lại?",
    "level": 3,
    "tag_ids": ["665dbc00000000000000000d"],
    "type": "multiple_choice",
    "choices": [
      { "text": "4", "is_correct": true },
      { "text": "3", "is_correct": false },
      { "text": "5", "is_correct": false }
    ],
    "answer_explanation": "Tổng cộng 12 nhiệm vụ cần hoàn thành trong 4 ngày.\nKế hoạch ban đầu: 3 nhiệm vụ/ngày × 4 ngày = 12 nhiệm vụ.\nNgày đầu chỉ làm 1 nhiệm vụ, còn lại 12 - 1 = 11 nhiệm vụ.\n11 nhiệm vụ phải hoàn thành trong 3 ngày còn lại.\nSố nhiệm vụ mỗi ngày: 11 ÷ 3 ≈ 4 (làm tròn vì phải chia đều).\nDo đó, đội cần làm 4 nhiệm vụ mỗi ngày.\nGiải quyết vấn đề yêu cầu phân tích và tính toán logic.\nKiểm tra số nhiệm vụ còn lại giúp xác định đáp án đúng.",
    "createdAt": "2025-05-12T10:00:00Z",
    "updatedAt": "2025-05-12T10:00:00Z"
  },
  {
    "_id": "665dbc050000000000000006",
    "question": "Một bể nước đầy sau 6 giờ nếu mở vòi A, hoặc 8 giờ nếu mở vòi B. Nếu mở cả hai vòi, bể đầy trong bao lâu?",
    "level": 4,
    "tag_ids": ["665dbc00000000000000000d"],
    "type": "multiple_choice",
    "choices": [
      { "text": "3.43 giờ", "is_correct": true },
      { "text": "4 giờ", "is_correct": false },
      { "text": "7 giờ", "is_correct": false }
    ],
    "answer_explanation": "Vòi A đầy bể trong 6 giờ, tốc độ 1/6 bể/giờ.\nVòi B đầy bể trong 8 giờ, tốc độ 1/8 bể/giờ.\nCả hai vòi cùng mở: tốc độ tổng = 1/6 + 1/8 = 4/24 + 3/24 = 7/24 bể/giờ.\nThời gian đầy bể: 1 ÷ (7/24) = 24/7 ≈ 3.43 giờ.\nCác lựa chọn khác không phù hợp với tính toán.\nGiải quyết vấn đề yêu cầu áp dụng logic toán học để tính thời gian.\nKiểm tra tốc độ và công thức giúp xác định đáp án đúng.",
    "createdAt": "2025-05-12T10:00:00Z",
    "updatedAt": "2025-05-12T10:00:00Z"
  },
  {
    "_id": "665dbc050000000000000007",
    "question": "Phát biểu: 'Nếu học chăm chỉ, bạn sẽ giỏi toán.' Bạn không giỏi toán. Phát biểu có đúng không?",
    "level": 3,
    "tag_ids": ["665dbc00000000000000000e"],
    "type": "multiple_choice",
    "choices": [
      { "text": "Bạn không học chăm chỉ", "is_correct": true },
      { "text": "Bạn học chăm chỉ", "is_correct": false },
      { "text": "Không đủ thông tin", "is_correct": false }
    ],
    "answer_explanation": "Phát biểu: Nếu học chăm chỉ (A) thì giỏi toán (B), tức A → B.\nBạn không giỏi toán (¬B).\nTheo logic, nếu A → B và ¬B, thì ¬A (modus tollens).\nDo đó, bạn không học chăm chỉ.\nLựa chọn 'học chăm chỉ' mâu thuẫn với phát biểu.\n'Không đủ thông tin' không đúng vì logic cho kết luận rõ.\nPhân tích phát biểu yêu cầu áp dụng luật logic.\nKiểm tra điều kiện và kết luận giúp xác định đáp án đúng.",
    "createdAt": "2025-05-12T10:00:00Z",
    "updatedAt": "2025-05-12T10:00:00Z"
  },
  {
    "_id": "665dbc050000000000000008",
    "question": "Phát biểu: 'Tất cả mèo đều thích cá.' Một con mèo không thích cá. Phát biểu này đúng hay sai?",
    "level": 2,
    "tag_ids": ["665dbc00000000000000000e"],
    "type": "multiple_choice",
    "choices": [
      { "text": "Sai", "is_correct": true },
      { "text": "Đúng", "is_correct": false },
      { "text": "Không xác định", "is_correct": false }
    ],
    "answer_explanation": "Phát biểu: 'Tất cả mèo đều thích cá.'\nMột con mèo không thích cá, tức tồn tại mèo không thỏa mãn phát biểu.\nPhát biểu 'tất cả' yêu cầu mọi mèo đều thích cá, nhưng ví dụ phản chứng cho thấy điều này sai.\nDo đó, phát biểu là sai.\nLựa chọn 'đúng' mâu thuẫn với dữ kiện.\n'Không xác định' không đúng vì có bằng chứng rõ ràng.\nPhân tích phát biểu yêu cầu kiểm tra tính đúng sai.\nKiểm tra ví dụ phản chứng giúp xác định đáp án đúng.",
    "createdAt": "2025-05-12T10:00:00Z",
    "updatedAt": "2025-05-12T10:00:00Z"
  },
  {
    "_id": "665dbc050000000000000009",
    "question": "Tiền đề: Tất cả chim đều bay. Tất cả chim sẻ là chim. Kết luận là gì?",
    "level": 1,
    "tag_ids": ["665dbc00000000000000000f"],
    "type": "multiple_choice",
    "choices": [
      { "text": "Tất cả chim sẻ đều bay", "is_correct": true },
      { "text": "Một số chim sẻ không bay", "is_correct": false },
      { "text": "Chim sẻ không phải chim", "is_correct": false }
    ],
    "answer_explanation": "Tiền đề 1: Tất cả chim đều bay.\nTiền đề 2: Tất cả chim sẻ là chim.\nTừ tiền đề 1, mọi chim đều bay.\nTừ tiền đề 2, chim sẻ thuộc nhóm chim.\nDo đó, tất cả chim sẻ đều bay.\nLựa chọn 'một số chim sẻ không bay' mâu thuẫn với tiền đề.\n'Chim sẻ không phải chim' sai vì tiền đề 2.\nTam đoạn luận yêu cầu suy luận logic từ hai tiền đề.\nKiểm tra tính hợp lệ của kết luận giúp xác định đáp án đúng.",
    "createdAt": "2025-05-12T10:00:00Z",
    "updatedAt": "2025-05-12T10:00:00Z"
  },
  {
    "_id": "665dbc05000000000000000a",
    "question": "Tiền đề: Tất cả học sinh giỏi đều chăm chỉ. Một số học sinh không chăm chỉ. Kết luận là gì?",
    "level": 3,
    "tag_ids": ["665dbc00000000000000000f"],
    "type": "multiple_choice",
    "choices": [
      { "text": "Một số học sinh không giỏi", "is_correct": true },
      { "text": "Tất cả học sinh đều giỏi", "is_correct": false },
      { "text": "Không có học sinh nào giỏi", "is_correct": false }
    ],
    "answer_explanation": "Tiền đề 1: Tất cả học sinh giỏi đều chăm chỉ.\nTiền đề 2: Một số học sinh không chăm chỉ.\nHọc sinh giỏi phải chăm chỉ (từ tiền đề 1).\nVì một số học sinh không chăm chỉ (tiền đề 2), họ không thể giỏi.\nDo đó, một số học sinh không giỏi.\nLựa chọn 'tất cả học sinh giỏi' mâu thuẫn với tiền đề 2.\n'Không có học sinh giỏi' không suy ra từ tiền đề.\nTam đoạn luận yêu cầu rút ra kết luận logic.\nKiểm tra điều kiện giúp xác định đáp án đúng.",
    "createdAt": "2025-05-12T10:00:00Z",
    "updatedAt": "2025-05-12T10:00:00Z"
  },
  {
    "_id": "665dbc05000000000000000b",
    "question": "Tập A: Người thích bóng đá. Tập B: Người thích bóng rổ. Một số người thích cả hai. Ai chắc chắn thuộc cả A và B?",
    "level": 2,
    "tag_ids": ["665dbc000000000000000010"],
    "type": "multiple_choice",
    "choices": [
      { "text": "Người thích cả bóng đá và bóng rổ", "is_correct": true },
      { "text": "Người chỉ thích bóng đá", "is_correct": false },
      { "text": "Người không thích môn nào", "is_correct": false }
    ],
    "answer_explanation": "Tập A: Người thích bóng đá. Tập B: Người thích bóng rổ.\nBiểu đồ Venn: A và B giao nhau tại những người thích cả hai.\nNgười thích cả bóng đá và bóng rổ thuộc vùng giao của A và B.\nNgười chỉ thích bóng đá thuộc A nhưng không thuộc B.\nNgười không thích môn nào không thuộc A hay B.\nBiểu đồ Venn yêu cầu phân tích mối quan hệ tập hợp.\nKiểm tra vùng giao của các tập giúp xác định đáp án đúng.",
    "createdAt": "2025-05-12T10:00:00Z",
    "updatedAt": "2025-05-12T10:00:00Z"
  },
  {
    "_id": "665dbc05000000000000000c",
    "question": "Tập X: Học sinh học toán. Tập Y: Học sinh học lý. Tất cả học sinh học lý đều học toán. Ai thuộc X nhưng không thuộc Y?",
    "level": 3,
    "tag_ids": ["665dbc000000000000000010"],
    "type": "multiple_choice",
    "choices": [
      { "text": "Học sinh chỉ học toán", "is_correct": true },
      { "text": "Học sinh học cả toán và lý", "is_correct": false },
      { "text": "Học sinh không học môn nào", "is_correct": false }
    ],
    "answer_explanation": "Tập X: Học toán. Tập Y: Học lý.\nTất cả học sinh học lý đều học toán, nên Y nằm trong X (Y ⊆ X).\nHọc sinh chỉ học toán thuộc X nhưng không thuộc Y (vùng X ngoài Y).\nHọc sinh học cả toán và lý thuộc cả X và Y.\nHọc sinh không học môn nào không thuộc X hay Y.\nBiểu đồ Venn yêu cầu phân tích vùng của các tập hợp.\nKiểm tra mối quan hệ giữa X và Y giúp xác định đáp án đúng.",
    "createdAt": "2025-05-12T10:00:00Z",
    "updatedAt": "2025-05-12T10:00:00Z"
  },
  {
    "_id": "665dbc05000000000000000d",
    "question": "Phát biểu: 'Nếu trời nắng, tôi đi dạo. Trời không nắng.' Phát biểu này đúng hay sai?",
    "level": 2,
    "tag_ids": ["665dbc000000000000000011"],
    "type": "multiple_choice",
    "choices": [
      { "text": "Không xác định", "is_correct": true },
      { "text": "Đúng", "is_correct": false },
      { "text": "Sai", "is_correct": false }
    ],
    "answer_explanation": "Phát biểu: Nếu trời nắng (A) thì đi dạo (B), tức A → B.\nTrời không nắng (¬A).\nTrong logic, nếu A → B và ¬A, không thể xác định B (đi dạo hay không).\nPhát biểu không nói gì về trường hợp trời không nắng.\nDo đó, không xác định được phát biểu đúng hay sai.\nLogic đúng/sai yêu cầu đánh giá giá trị logic của phát biểu.\nKiểm tra các trường hợp của A → B giúp xác định đáp án đúng.",
    "createdAt": "2025-05-12T10:00:00Z",
    "updatedAt": "2025-05-12T10:00:00Z"
  },
  {
    "_id": "665dbc05000000000000000e",
    "question": "Phát biểu: 'Tất cả học sinh đều thích học.' Có một học sinh không thích học. Phát biểu đúng hay sai?",
    "level": 1,
    "tag_ids": ["665dbc000000000000000011"],
    "type": "multiple_choice",
    "choices": [
      { "text": "Sai", "is_correct": true },
      { "text": "Đúng", "is_correct": false },
      { "text": "Không xác định", "is_correct": false }
    ],
    "answer_explanation": "Phát biểu: Tất cả học sinh đều thích học.\nCó một học sinh không thích học, tức tồn tại phản chứng.\nPhát biểu 'tất cả' yêu cầu mọi học sinh đều thích học, nhưng phản chứng cho thấy điều này sai.\nDo đó, phát biểu là sai.\nLựa chọn 'đúng' mâu thuẫn với dữ kiện.\n'Không xác định' không đúng vì có bằng chứng rõ ràng.\nLogic đúng/sai yêu cầu kiểm tra tính đúng của phát biểu.\nKiểm tra phản chứng giúp xác định đáp án đúng.",
    "createdAt": "2025-05-12T10:00:00Z",
    "updatedAt": "2025-05-12T10:00:00Z"
  },
  {
    "_id": "665dbc05000000000000000f",
    "question": "Một cửa hàng giảm giá 20% cho sản phẩm giá 500.000 đồng. Giá sau giảm là bao nhiêu?",
    "level": 1,
    "tag_ids": ["665dbc000000000000000012"],
    "type": "multiple_choice",
    "choices": [
      { "text": "400.000 đồng", "is_correct": true },
      { "text": "450.000 đồng", "is_correct": false },
      { "text": "480.000 đồng", "is_correct": false }
    ],
    "answer_explanation": "Giá gốc sản phẩm: 500.000 đồng.\nGiảm giá 20%, tức giảm 20% × 500.000 = 100.000 đồng.\nGiá sau giảm: 500.000 - 100.000 = 400.000 đồng.\nCách khác: Giá sau giảm = 80% × 500.000 = 400.000 đồng.\nCác lựa chọn khác không phù hợp với phép tính.\nSuy luận toán học yêu cầu áp dụng phép tính phần trăm.\nKiểm tra phép tính giảm giá giúp xác định đáp án đúng.",
    "createdAt": "2025-05-12T10:00:00Z",
    "updatedAt": "2025-05-12T10:00:00Z"
  },
  {
    "_id": "665dbc050000000000000010",
    "question": "Một người đi từ A đến B với tốc độ 40 km/h và quay lại với tốc độ 60 km/h. Tốc độ trung bình của toàn chuyến đi là bao nhiêu?",
    "level": 4,
    "tag_ids": ["665dbc000000000000000012"],
    "type": "multiple_choice",
    "choices": [
      { "text": "48 km/h", "is_correct": true },
      { "text": "50 km/h", "is_correct": false },
      { "text": "52 km/h", "is_correct": false }
    ],
    "answer_explanation": "Giả sử quãng đường từ A đến B là S km.\nThời gian đi: S ÷ 40 giờ. Thời gian về: S ÷ 60 giờ.\nTổng quãng đường: 2S km.\nTổng thời gian: (S/40) + (S/60) = S(3/120 + 2/120) = S × 5/120 = S/24 giờ.\nTốc độ trung bình = Tổng quãng đường ÷ Tổng thời gian = 2S ÷ (S/24) = 48 km/h.\nCác lựa chọn khác không phù hợp với công thức tốc độ trung bình.\nSuy luận toán học yêu cầu tính toán chính xác.\nKiểm tra công thức tốc độ giúp xác định đáp án đúng.",
    "createdAt": "2025-05-12T10:00:00Z",
    "updatedAt": "2025-05-12T10:00:00Z"
  },
  {
    "_id": "665dbc050000000000000011",
    "question": "Các số: 4, 9, 16, 25, 30. Số nào không thuộc nhóm?",
    "level": 2,
    "tag_ids": ["665dbc000000000000000013"],
    "type": "multiple_choice",
    "choices": [
      { "text": "30", "is_correct": true },
      { "text": "9", "is_correct": false },
      { "text": "16", "is_correct": false }
    ],
    "answer_explanation": "Các số: 4, 9, 16, 25, 30.\nKiểm tra: 4 = 2², 9 = 3², 16 = 4², 25 = 5² là số chính phương.\n30 không phải số chính phương (5² = 25, 6² = 36).\nDo đó, 30 không thuộc nhóm số chính phương.\nLựa chọn 9 và 16 đều là số chính phương, thuộc nhóm.\nTìm điểm khác biệt yêu cầu nhận diện đặc điểm chung của nhóm.\nKiểm tra tính chất số học giúp xác định đáp án đúng.",
    "createdAt": "2025-05-12T10:00:00Z",
    "updatedAt": "2025-05-12T10:00:00Z"
  },
  {
    "_id": "665dbc050000000000000012",
    "question": "Các hình: vuông, tam giác, hình tròn, hình chữ nhật, ngũ giác. Hình nào không thuộc nhóm?",
    "level": 2,
    "tag_ids": ["665dbc000000000000000013"],
    "type": "multiple_choice",
    "choices": [
      { "text": "Hình tròn", "is_correct": true },
      { "text": "Vuông", "is_correct": false },
      { "text": "Tam giác", "is_correct": false }
    ],
    "answer_explanation": "Các hình: vuông, tam giác, hình tròn, hình chữ nhật, ngũ giác.\nVuông, tam giác, hình chữ nhật, ngũ giác là đa giác (có cạnh thẳng).\nHình tròn không phải đa giác vì có đường cong.\nDo đó, hình tròn không thuộc nhóm đa giác.\nLựa chọn vuông và tam giác đều là đa giác, thuộc nhóm.\nTìm điểm khác biệt yêu cầu nhận diện đặc điểm chung của nhóm.\nKiểm tra tính chất hình học giúp xác định đáp án đúng.",
    "createdAt": "2025-05-12T10:00:00Z",
    "updatedAt": "2025-05-12T10:00:00Z"
  },
  {
    "_id": "665dbc050000000000000013",
    "question": "Cho A: 'Trời mưa', B: 'Tôi ở nhà'. Phát biểu (A OR B) AND NOT A có nghĩa là gì?",
    "level": 3,
    "tag_ids": ["665dbc000000000000000014"],
    "type": "multiple_choice",
    "choices": [
      { "text": "Trời không mưa và tôi ở nhà", "is_correct": true },
      { "text": "Trời mưa và tôi ở nhà", "is_correct": false },
      { "text": "Trời không mưa và tôi không ở nhà", "is_correct": false }
    ],
    "answer_explanation": "A: Trời mưa, B: Tôi ở nhà.\nPhát biểu: (A OR B) AND NOT A.\nA OR B: Trời mưa hoặc tôi ở nhà.\nNOT A: Trời không mưa.\n(A OR B) AND NOT A: (Trời mưa hoặc tôi ở nhà) và trời không mưa.\nĐiều này đúng khi trời không mưa (NOT A) và tôi ở nhà (B).\nDo đó, nghĩa là trời không mưa và tôi ở nhà.\nLogic Boole yêu cầu phân tích toán tử logic.\nKiểm tra giá trị của từng phần giúp xác định đáp án đúng.",
    "createdAt": "2025-05-12T10:00:00Z",
    "updatedAt": "2025-05-12T10:00:00Z"
  },
  {
    "_id": "665dbc050000000000000014",
    "question": "Cho X: 'Anh ấy học giỏi', Y: 'Anh ấy chăm chỉ'. Phát biểu NOT (X AND Y) có nghĩa là gì?",
    "level": 3,
    "tag_ids": ["665dbc000000000000000014"],
    "type": "multiple_choice",
    "choices": [
      { "text": "Anh ấy không học giỏi hoặc không chăm chỉ", "is_correct": true },
      { "text": "Anh ấy học giỏi và chăm chỉ", "is_correct": false },
      { "text": "Anh ấy không học giỏi và không chăm chỉ", "is_correct": false }
    ],
    "answer_explanation": "X: Anh ấy học giỏi, Y: Anh ấy chăm chỉ.\nPhát biểu: NOT (X AND Y).\nX AND Y: Anh ấy học giỏi và chăm chỉ.\nNOT (X AND Y): Không phải (học giỏi và chăm chỉ).\nTheo luật De Morgan, NOT (X AND Y) = NOT X OR NOT Y.\nTức là anh ấy không học giỏi hoặc không chăm chỉ.\nLựa chọn khác không phù hợp với biểu thức logic.\nLogic Boole yêu cầu áp dụng toán tử và luật logic.\nKiểm tra luật De Morgan giúp xác định đáp án đúng.",
    "createdAt": "2025-05-12T10:00:00Z",
    "updatedAt": "2025-05-12T10:00:00Z"
  }
]
